{"value_line": 5.028628245101407, "price_to_value": 0.4374950568563326, "valuation_score": 100, "quality_score": 50.0, "mktcap": 2104.823362562963, "eps_excl": 0.0027, "yoy": 1.02871090620026, "yoy_source": "akshare东方财富扣非净利润同比", "latest_excl_eps": null, "prev_excl_eps": null, "latest_report": "2025-03-31 00:00:00", "annual_report": "2024-12-31 00:00:00", "data_source": "akshare/eastmoney_indicator", "total_share": 95673789207.40741, "eps_excl_raw": 0.0027, "eps_adjustment_factor": 1.0, "eps_excl_source": "年报扣非EPS", "eps_bonus_detail": null, "bvps": null}