{"value_line": 33.9381241636024, "price_to_value": 0.7740557454903111, "valuation_score": 67.992036358527, "quality_score": 65.0, "mktcap": 443.8222502160413, "eps_excl": 2.106, "yoy": -0.12346316835226, "yoy_source": "akshare东方财富扣非净利润同比", "latest_excl_eps": 1.12, "prev_excl_eps": null, "latest_report": "2025-06-30 00:00:00", "annual_report": "2024-12-31 00:00:00", "data_source": "akshare/eastmoney_indicator", "total_share": 1689464218.5612535, "eps_excl_raw": 2.106, "eps_adjustment_factor": 1.0, "eps_excl_source": "年报扣非EPS", "eps_bonus_detail": null, "bvps": null}