{"value_line": 6.4612445527614195, "price_to_value": 2.7007180826396957, "valuation_score": 0, "quality_score": 50.97787722023233, "mktcap": 91.91294321119999, "eps_excl": 0.05, "yoy": 0.25962075234684, "yoy_source": "akshare东方财富扣非净利润同比", "latest_excl_eps": null, "prev_excl_eps": null, "latest_report": "2026-03-31 00:00:00", "annual_report": "2025-12-31 00:00:00", "data_source": "akshare/eastmoney_indicator", "total_share": 526721737.59999996, "eps_excl_raw": 0.05, "eps_adjustment_factor": 1.0, "eps_excl_source": "年报扣非EPS", "eps_bonus_detail": null, "bvps": null}