{"value_line": 6.400607928048859, "price_to_value": 1.0764602483783638, "valuation_score": 24.791393088805165, "quality_score": 57.5, "mktcap": 44.62120421485365, "eps_excl": 0.041, "yoy": 2.92271234754112, "yoy_source": "akshare东方财富扣非净利润同比", "latest_excl_eps": 0.041, "prev_excl_eps": null, "latest_report": "2024-12-31 00:00:00", "annual_report": "2024-12-31 00:00:00", "data_source": "akshare/eastmoney_indicator", "total_share": 647622702.6829268, "eps_excl_raw": 0.041, "eps_adjustment_factor": 1.0, "eps_excl_source": "年报扣非EPS", "eps_bonus_detail": null, "bvps": null}