{"value_line": 24.630739747159858, "price_to_value": 0.5700194206152065, "valuation_score": 97.14008276925622, "quality_score": 64.19920999483158, "mktcap": 114.56217502496501, "eps_excl": 1.3289, "yoy": 0.08817217133996999, "yoy_source": "akshare东方财富扣非净利润同比", "latest_excl_eps": 1.3289, "prev_excl_eps": null, "latest_report": "2024-12-31 00:00:00", "annual_report": "2024-12-31 00:00:00", "data_source": "akshare/eastmoney_indicator", "total_share": 815969907.5852209, "eps_excl_raw": 1.3289, "eps_adjustment_factor": 1.0, "eps_excl_source": "年报扣非EPS", "eps_bonus_detail": null, "bvps": null}