{"value_line": 15.59863062220142, "price_to_value": 0.8404583913501119, "valuation_score": 58.505944092841155, "quality_score": 42.75, "mktcap": 98.21114413333187, "eps_excl": 0.91, "yoy": -0.13921504906391, "yoy_source": "akshare东方财富扣非净利润同比", "latest_excl_eps": 0.91, "prev_excl_eps": null, "latest_report": "2024-12-31 00:00:00", "annual_report": "2024-12-31 00:00:00", "data_source": "akshare/eastmoney_indicator", "total_share": 749131534.1978022, "eps_excl_raw": 0.91, "eps_adjustment_factor": 1.0, "eps_excl_source": "年报扣非EPS", "eps_bonus_detail": null, "bvps": null}