{"value_line": 9.725438148264761, "price_to_value": 4.19312727902918, "valuation_score": 0, "quality_score": 54.35403042822737, "mktcap": 224.68544939250287, "eps_excl": 0.3088235294117647, "yoy": 0.22800186616457002, "yoy_source": "akshare东方财富扣非净利润同比", "latest_excl_eps": null, "prev_excl_eps": null, "latest_report": "2025-03-31 00:00:00", "annual_report": "2024-12-31 00:00:00", "data_source": "akshare/eastmoney_indicator", "total_share": 550969714.0571429, "eps_excl_raw": 0.35, "eps_adjustment_factor": 1.1333333333333333, "eps_excl_source": "年报扣非EPS送转可比口径(原始0.35/月度加权1.1333)", "eps_bonus_detail": {"bonus_ratio_per_10": 2.0, "ex_right_date": "2025-05-09", "post_months": 8}, "bvps": null}