{"value_line": 27.083552152622598, "price_to_value": 2.2157359441563877, "valuation_score": 0, "quality_score": 88.75, "mktcap": 61.59370489540285, "eps_excl": 1.05, "yoy": 0.5344997815032, "yoy_source": "akshare东方财富扣非净利润同比", "latest_excl_eps": 0.6, "prev_excl_eps": null, "latest_report": "2025-06-30 00:00:00", "annual_report": "2024-12-31 00:00:00", "data_source": "akshare/eastmoney_indicator", "total_share": 102639068.31428571, "eps_excl_raw": 1.05, "eps_adjustment_factor": 1.0, "eps_excl_source": "年报扣非EPS", "eps_bonus_detail": null, "bvps": null}