{"value_line": 15.86933594982957, "price_to_value": 1.898000023140444, "valuation_score": 0, "quality_score": 23.0, "mktcap": 106.90029924225716, "eps_excl": 0.42, "yoy": -0.50232237262296, "yoy_source": "akshare东方财富扣非净利润同比", "latest_excl_eps": 0.42, "prev_excl_eps": null, "latest_report": "2024-12-31 00:00:00", "annual_report": "2024-12-31 00:00:00", "data_source": "akshare/eastmoney_indicator", "total_share": 354914672.11904764, "eps_excl_raw": 0.42, "eps_adjustment_factor": 1.0, "eps_excl_source": "年报扣非EPS", "eps_bonus_detail": null, "bvps": null}