{"value_line": 6.3390535488000275, "price_to_value": 3.024110752878693, "valuation_score": 0, "quality_score": 33.9975, "mktcap": 29.960449370927275, "eps_excl": 0.2599, "yoy": -0.97479776195882, "yoy_source": "akshare东方财富扣非净利润同比", "latest_excl_eps": null, "prev_excl_eps": null, "latest_report": "2026-03-31 00:00:00", "annual_report": "2025-12-31 00:00:00", "data_source": "akshare/eastmoney_indicator", "total_share": 156288207.46440935, "eps_excl_raw": 0.2599, "eps_adjustment_factor": 1.0, "eps_excl_source": "年报扣非EPS", "eps_bonus_detail": null, "bvps": null}