{"value_line": 11.755743504318717, "price_to_value": 2.4209442805165513, "valuation_score": 0, "quality_score": 15.0, "mktcap": 23.85023693665298, "eps_excl": 0.0974, "yoy": -0.51309056024259, "yoy_source": "akshare东方财富扣非净利润同比", "latest_excl_eps": 0.0974, "prev_excl_eps": null, "latest_report": "2024-12-31 00:00:00", "annual_report": "2024-12-31 00:00:00", "data_source": "akshare/eastmoney_indicator", "total_share": 83802659.65092403, "eps_excl_raw": 0.0974, "eps_adjustment_factor": 1.0, "eps_excl_source": "年报扣非EPS", "eps_bonus_detail": null, "bvps": null}