{"value_line": 14.747147481859784, "price_to_value": 0.6374114052607652, "valuation_score": 87.51265639131925, "quality_score": 51.1325, "mktcap": 28.22326538169305, "eps_excl": 0.1453, "yoy": 4.42663804175897, "yoy_source": "akshare东方财富扣非净利润同比", "latest_excl_eps": null, "prev_excl_eps": null, "latest_report": "2025-03-31 00:00:00", "annual_report": "2024-12-31 00:00:00", "data_source": "akshare/eastmoney_indicator", "total_share": 300247504.06056434, "eps_excl_raw": 0.1453, "eps_adjustment_factor": 1.0, "eps_excl_source": "年报扣非EPS", "eps_bonus_detail": null, "bvps": null}