{"value_line": 14.298797420326942, "price_to_value": 0.4811593449264133, "valuation_score": 100, "quality_score": 62.225, "mktcap": 246.87870933492047, "eps_excl": 0.289, "yoy": 1.87286726167299, "yoy_source": "akshare东方财富扣非净利润同比", "latest_excl_eps": 0.289, "prev_excl_eps": null, "latest_report": "2024-12-31 00:00:00", "annual_report": "2024-12-31 00:00:00", "data_source": "akshare/eastmoney_indicator", "total_share": 3588353333.356402, "eps_excl_raw": 0.289, "eps_adjustment_factor": 1.0, "eps_excl_source": "年报扣非EPS", "eps_bonus_detail": null, "bvps": null}