{"value_line": 14.96198428954289, "price_to_value": 1.1402230927299821, "valuation_score": 15.682415324288268, "quality_score": 61.98045866136983, "mktcap": 140.08993839510353, "eps_excl": 0.85, "yoy": 0.12680786276634, "yoy_source": "akshare东方财富扣非净利润同比", "latest_excl_eps": 0.56, "prev_excl_eps": null, "latest_report": "2025-06-30 00:00:00", "annual_report": "2024-12-31 00:00:00", "data_source": "akshare/eastmoney_indicator", "total_share": 821160248.5058824, "eps_excl_raw": 0.85, "eps_adjustment_factor": 1.0, "eps_excl_source": "年报扣非EPS", "eps_bonus_detail": null, "bvps": null}