{"value_line": 14.583803907547878, "price_to_value": 0.5890095652996422, "valuation_score": 94.42720495719398, "quality_score": 58.997798852083584, "mktcap": 99.94673263202549, "eps_excl": 0.51, "yoy": 0.22139083746429, "yoy_source": "akshare东方财富扣非净利润同比", "latest_excl_eps": null, "prev_excl_eps": null, "latest_report": "2025-03-31 00:00:00", "annual_report": "2024-12-31 00:00:00", "data_source": "akshare/eastmoney_indicator", "total_share": 1163524244.8431373, "eps_excl_raw": 0.51, "eps_adjustment_factor": 1.0, "eps_excl_source": "年报扣非EPS", "eps_bonus_detail": null, "bvps": null}