{"value_line": 9.639517283649234, "price_to_value": 1.188856211652705, "valuation_score": 8.734826906756421, "quality_score": 52.370593544202, "mktcap": 113.04347898791765, "eps_excl": 0.51, "yoy": 0.23635303218632, "yoy_source": "akshare东方财富扣非净利润同比", "latest_excl_eps": 0.51, "prev_excl_eps": null, "latest_report": "2024-12-31 00:00:00", "annual_report": "2024-12-31 00:00:00", "data_source": "akshare/eastmoney_indicator", "total_share": 986417792.2156862, "eps_excl_raw": 0.51, "eps_adjustment_factor": 1.0, "eps_excl_source": "年报扣非EPS", "eps_bonus_detail": null, "bvps": null}