{"value_line": 26.233507079235668, "price_to_value": 1.113080302675671, "valuation_score": 19.559956760618423, "quality_score": 66.64997499991024, "mktcap": 254.4446324939504, "eps_excl": 1.21, "yoy": 0.18114242856989002, "yoy_source": "akshare东方财富扣非净利润同比", "latest_excl_eps": 1.21, "prev_excl_eps": null, "latest_report": "2024-12-31 00:00:00", "annual_report": "2024-12-31 00:00:00", "data_source": "akshare/eastmoney_indicator", "total_share": 871385727.7190082, "eps_excl_raw": 1.21, "eps_adjustment_factor": 1.0, "eps_excl_source": "年报扣非EPS", "eps_bonus_detail": null, "bvps": null}