{"value_line": 67.63853327555337, "price_to_value": 1.350265825959438, "valuation_score": 0, "quality_score": 59.55129027193358, "mktcap": 71.54472548001225, "eps_excl": 3.3474, "yoy": -0.06483502390971001, "yoy_source": "akshare东方财富扣非净利润同比", "latest_excl_eps": 3.3474, "prev_excl_eps": null, "latest_report": "2024-12-31 00:00:00", "annual_report": "2024-12-31 00:00:00", "data_source": "akshare/eastmoney_indicator", "total_share": 78336500.03286132, "eps_excl_raw": 3.3474, "eps_adjustment_factor": 1.0, "eps_excl_source": "年报扣非EPS", "eps_bonus_detail": null, "bvps": null}